hat/doit/pep517.py
hat/doit/sphinx/__init__.py
hat/doit/clang/__init__.py
hat/doit/eslint/__init__.py
hat/doit/js.py
hat/doit/common.py
hat/doit/sphinx/static/hat.css
hat/doit/docs.py
hat/doit/pytest.py
hat/doit/eslint/ts.yaml
hat/doit/clang/clang-format.yaml
hat/doit/__init__.py
hat/doit/c.py
hat/doit/eslint/js.yaml
hat/doit/py.py
hat_doit-0.16.2.dist-info/LICENSE
hat_doit-0.16.2.dist-info/METADATA
hat_doit-0.16.2.dist-info/WHEEL
hat_doit-0.16.2.dist-info/RECORD
