Metadata-Version: 2.1
Name: hat-doit
Version: 0.16.2
Summary: Hat build utility functions
License: Apache-2.0
Classifier: Programming Language :: Python :: 3
Classifier: License :: OSI Approved :: Apache Software License
Requires-Dist: doit >=0.36.0
Requires-Dist: flake8 >=7.1.2
Requires-Dist: furo >=2024.8.6
Requires-Dist: mkwhl ~=0.3.1
Requires-Dist: packaging >=24.2
Requires-Dist: pdoc >=15.0.0
Requires-Dist: pytest >=8.3.5
Requires-Dist: pytest-asyncio >=0.25.1
Requires-Dist: pytest-cov >=6.0.0
Requires-Dist: pytest-timeout >=2.3.1
Requires-Dist: sphinx >=8.2.3
Requires-Dist: tomli >=2.0.1; python_version<'3.11'
Requires-Dist: watchdog >=6.0.0
Requires-Python: >=3.10
Project-URL: Homepage, http://hat-open.com
Project-URL: Repository, https://github.com/hat-open/hat-doit.git
